Metadata-Version: 2.1
Name: aistis-calculator
Version: 1.0
Summary: Console application that calculates
Home-page: https://github.com/petriukas/Calculator.git
Author: Aistis Jampolskis
Author-email: aistis.jampolskis@gmail.com
Classifier: Programming Language :: Python :: 3
Classifier: License :: OSI Approved :: MIT License
Classifier: Operating System :: OS Independent
